tests/__init__.py
tests/conftest.py
tests/test_aio_clients.py
tests/test_clients.py
tinkoff_voicekit_client/__init__.py
tinkoff_voicekit_client/Operations/__init__.py
tinkoff_voicekit_client/Operations/aio_long_running.py
tinkoff_voicekit_client/Operations/config_schema.py
tinkoff_voicekit_client/Operations/helper_operations.py
tinkoff_voicekit_client/Operations/long_running.py
tinkoff_voicekit_client/STT/__init__.py
tinkoff_voicekit_client/STT/aio_client_stt.py
tinkoff_voicekit_client/STT/client_stt.py
tinkoff_voicekit_client/STT/config_schema.py
tinkoff_voicekit_client/STT/helper_stt.py
tinkoff_voicekit_client/TTS/__init__.py
tinkoff_voicekit_client/TTS/aio_client_tts.py
tinkoff_voicekit_client/TTS/client_tts.py
tinkoff_voicekit_client/TTS/config_schema.py
tinkoff_voicekit_client/TTS/configurator_codec.py
tinkoff_voicekit_client/TTS/helper_tts.py
tinkoff_voicekit_client/TTS/opuslibwin/libeay32.dll
tinkoff_voicekit_client/TTS/opuslibwin/libgcc_s_sjlj-1.dll
tinkoff_voicekit_client/TTS/opuslibwin/libogg-0.dll
tinkoff_voicekit_client/TTS/opuslibwin/libopusfile-0.dll
tinkoff_voicekit_client/TTS/opuslibwin/libopusfile.a
tinkoff_voicekit_client/TTS/opuslibwin/libopusfile.dll.a
tinkoff_voicekit_client/TTS/opuslibwin/libopusurl-0.dll
tinkoff_voicekit_client/TTS/opuslibwin/libopusurl.a
tinkoff_voicekit_client/TTS/opuslibwin/libopusurl.dll.a
tinkoff_voicekit_client/TTS/opuslibwin/libwinpthread-1.dll
tinkoff_voicekit_client/TTS/opuslibwin/opus.dll
tinkoff_voicekit_client/Uploader/__init__.py
tinkoff_voicekit_client/Uploader/aio_uploader.py
tinkoff_voicekit_client/Uploader/uploader.py
tinkoff_voicekit_client/aio_voicekit/__init__.py
tinkoff_voicekit_client/speech_utils/__init__.py
tinkoff_voicekit_client/speech_utils/config_data.py
tinkoff_voicekit_client/speech_utils/infrastructure.py
tinkoff_voicekit_client/speech_utils/metadata.py
tinkoff_voicekit_client/speech_utils/user_utils.py
tinkoff_voicekit_client/speech_utils/BaseClient/__init__.py
tinkoff_voicekit_client-0.3.3.dist-info/LICENSE
tinkoff_voicekit_client-0.3.3.dist-info/METADATA
tinkoff_voicekit_client-0.3.3.dist-info/WHEEL
tinkoff_voicekit_client-0.3.3.dist-info/top_level.txt
tinkoff_voicekit_client-0.3.3.dist-info/RECORD
