Metadata-Version: 2.1
Name: tinkoff-voicekit-client
Version: 0.3.3
Summary: Python Tinkoff Speech API
Home-page: UNKNOWN
Author: Tinkoff Speech Team
License: Apache License Version 2.0
Platform: UNKNOWN
Requires-Python: >=3.6
Requires-Dist: boto3 (>=1.12.27)
Requires-Dist: aioboto3 (~=8.3.0)
Requires-Dist: google (>=2.0.2)
Requires-Dist: jsonschema (>=3.0.1)
Requires-Dist: opuslib (==3.0.1)
Requires-Dist: grpcio (>=1.24.0)
Requires-Dist: grpcio-tools (>=1.24.0)
Requires-Dist: googleapis-common-protos (>=1.6.0)
Requires-Dist: requests (>=2.21.0)
Requires-Dist: pytest-asyncio (>=0.14.0)
Requires-Dist: pytest (>=6.2.1)
Requires-Dist: setuptools (>=50.3.2)
